Level2_FSM_Logics/1_Traffic_controller.v
module traffic_controller(

    input clk,
    input reset,
    input ped_button,

    output reg NS_R,
    output reg NS_Y,
    output reg NS_G,

    output reg EW_R,
    output reg EW_Y,
    output reg EW_G

);

reg [2:0] state;
reg [2:0] count;
reg ped_request;

parameter S0 = 2'b000;
parameter S1 = 2'b001;
parameter S2 = 2'b010;
parameter S3 = 2'b011;
parameter S4 = 3'b100;

always @(posedge clk or posedge reset)
begin

    if(reset)
    begin
        state <= S0;
        count <= 0;
        ped_request <= 0;
    end

    else
    begin
        if(ped_button)
            ped_request <= 1;

        case(state)

            S0:
            begin
                if(count == 4)
                begin
                    state <= S1;
                    count <= 0;
                end
                else
                    count <= count + 1;
            end

            S1:
            begin
                if(count == 1)
                begin

                    if(ped_request)
                        state <= S4;
                    else
                        state <= S2;

                    count <= 0;

                end
                else
                    count <= count + 1;
            end 

            S2:
            begin
                if(count == 4)
                begin
                    state <= S3;
                    count <= 0;
                end
                else
                    count <= count + 1;
            end

            S3:
            begin
                if(count == 1)
                begin
                    state <= S0;
                    count <= 0;
                end
                else
                    count <= count + 1;
            end

            S4:
            begin

                if(count == 2)
                begin
                    state <= S2;
                    count <= 0;
                    ped_request <= 0;
                end

                else
                    count <= count + 1;
            end

        endcase

    end

end

always @(*)
begin

    NS_R = 0;
    NS_Y = 0;
    NS_G = 0;

    EW_R = 0;
    EW_Y = 0;
    EW_G = 0;

    case(state)

        S0:
        begin
            NS_G = 1;
            EW_R = 1;
        end

        S1:
        begin
            NS_Y = 1;
            EW_R = 1;
        end

        S2:
        begin
            NS_R = 1;
            EW_G = 1;
        end

        S3:
        begin
            NS_R = 1;
            EW_Y = 1;
        end

        S4:
        begin
            NS_R = 1;
            EW_R = 1;
        end

    endcase

end

endmodule

Level2_FSM_Logics/1_Traffic_controller_tb.v
`timescale 1ns/1ps

module traffic_controller_tb;

reg clk;
reg reset;
reg ped_button;

wire NS_R;
wire NS_Y;
wire NS_G;

wire EW_R;
wire EW_Y;
wire EW_G;

traffic_controller uut(

    .clk(clk),
    .reset(reset),
    .ped_button(ped_button),

    .NS_R(NS_R),
    .NS_Y(NS_Y),
    .NS_G(NS_G),

    .EW_R(EW_R),
    .EW_Y(EW_Y),
    .EW_G(EW_G)

);

always #5 clk = ~clk;

initial begin

    $dumpfile("1_traffic_controller.vcd");
    $dumpvars(0, traffic_controller_tb);

    clk = 0;
    reset = 1;
    

    #10;
    reset = 0;

    ped_button = 0;

    #35;
    ped_button = 1;

    #10;
    ped_button = 0;

    #500;

    $finish;

end

endmodule

Level2_FSM_Logics/1_traffic_controller.vcd
$date
	Sun Jul 19 19:18:07 2026
$end
$version
	Icarus Verilog
$end
$timescale
	1ps
$end
$scope module traffic_controller_tb $end
$var wire 1 ! NS_Y $end
$var wire 1 " NS_R $end
$var wire 1 # NS_G $end
$var wire 1 $ EW_Y $end
$var wire 1 % EW_R $end
$var wire 1 & EW_G $end
$var reg 1 ' clk $end
$var reg 1 ( ped_button $end
$var reg 1 ) reset $end
$scope module uut $end
$var wire 1 ' clk $end
$var wire 1 ( ped_button $end
$var wire 1 ) reset $end
$var parameter 2 * S0 $end
$var parameter 2 + S1 $end
$var parameter 2 , S2 $end
$var parameter 2 - S3 $end
$var parameter 3 . S4 $end
$var reg 1 & EW_G $end
$var reg 1 % EW_R $end
$var reg 1 $ EW_Y $end
$var reg 1 # NS_G $end
$var reg 1 " NS_R $end
$var reg 1 ! NS_Y $end
$var reg 3 / count [2:0] $end
$var reg 1 0 ped_request $end
$var reg 3 1 state [2:0] $end
$upscope $end
$upscope $end
$enddefinitions $end
$comment Show the parameter values. $end
$dumpall
b100 .
b11 -
b10 ,
b1 +
b0 *
$end
#0
$dumpvars
b0 1
00
b0 /
1)
x(
0'
0&
1%
0$
1#
0"
0!
$end
#5000
1'
#10000
0'
0(
0)
#15000
b1 /
1'
#20000
0'
#25000
b10 /
1'
#30000
0'
#35000
b11 /
1'
#40000
0'
#45000
b100 /
10
1'
1(
#50000
0'
#55000
1!
1%
0#
b0 /
b1 1
1'
0(
#60000
0'
#65000
b1 /
1'
#70000
0'
#75000
1"
1%
0!
b0 /
b100 1
1'
#80000
0'
#85000
b1 /
1'
#90000
0'
#95000
b10 /
1'
#100000
0'
#105000
1&
0%
1"
00
b0 /
b10 1
1'
#110000
0'
#115000
b1 /
1'
#120000
0'
#125000
b10 /
1'
#130000
0'
#135000
b11 /
1'
#140000
0'
#145000
b100 /
1'
#150000
0'
#155000
1$
0&
1"
b0 /
b11 1
1'
#160000
0'
#165000
b1 /
1'
#170000
0'
#175000
1%
1#
0$
0"
b0 /
b0 1
1'
#180000
0'
#185000
b1 /
1'
#190000
0'
#195000
b10 /
1'
#200000
0'
#205000
b11 /
1'
#210000
0'
#215000
b100 /
1'
#220000
0'
#225000
1!
1%
0#
b0 /
b1 1
1'
#230000
0'
#235000
b1 /
1'
#240000
0'
#245000
1&
1"
0%
0!
b0 /
b10 1
1'
#250000
0'
#255000
b1 /
1'
#260000
0'
#265000
b10 /
1'
#270000
0'
#275000
b11 /
1'
#280000
0'
#285000
b100 /
1'
#290000
0'
#295000
1$
0&
1"
b0 /
b11 1
1'
#300000
0'
#305000
b1 /
1'
#310000
0'
#315000
1%
1#
0$
0"
b0 /
b0 1
1'
#320000
0'
#325000
b1 /
1'
#330000
0'
#335000
b10 /
1'
#340000
0'
#345000
b11 /
1'
#350000
0'
#355000
b100 /
1'
#360000
0'
#365000
1!
1%
0#
b0 /
b1 1
1'
#370000
0'
#375000
b1 /
1'
#380000
0'
#385000
1&
1"
0%
0!
b0 /
b10 1
1'
#390000
0'
#395000
b1 /
1'
#400000
0'
#405000
b10 /
1'
#410000
0'
#415000
b11 /
1'
#420000
0'
#425000
b100 /
1'
#430000
0'
#435000
1$
0&
1"
b0 /
b11 1
1'
#440000
0'
#445000
b1 /
1'
#450000
0'
#455000
1%
1#
0$
0"
b0 /
b0 1
1'
#460000
0'
#465000
b1 /
1'
#470000
0'
#475000
b10 /
1'
#480000
0'
#485000
b11 /
1'
#490000
0'
#495000
b100 /
1'
#500000
0'
#505000
1!
1%
0#
b0 /
b1 1
1'
#510000
0'
#515000
b1 /
1'
#520000
0'
#525000
1&
1"
0%
0!
b0 /
b10 1
1'
#530000
0'
#535000
b1 /
1'
#540000
0'
#545000
b10 /
1'
#550000
0'
#555000
b11 /
1'
