Level3_UART_Communication/1_UART.v
module uart_tx(

    input clk,
    input reset,
    input start,
    input [7:0] data_in,

    output reg tx,
    output reg busy

);

reg [1:0] state;
reg [2:0] bit_index;
reg [7:0] shift_reg;

parameter IDLE  = 2'b00;
parameter START = 2'b01;
parameter DATA  = 2'b10;
parameter STOP  = 2'b11;

always @(posedge clk or posedge reset)
begin

    if(reset)
    begin
        state <= IDLE;
        tx <= 1;
        busy <= 0;
        bit_index <= 0;
    end

    else
    begin

        case(state)

            IDLE:
            begin
                tx <= 1;
                busy <= 0;

                if(start)
                begin
                    shift_reg <= data_in;
                    bit_index <= 0;
                    busy <= 1;
                    state <= START;
                end
            end

            START:
            begin
                tx <= 0;
                state <= DATA;
            end

            DATA:
            begin

                tx <= shift_reg[bit_index];

                if(bit_index == 7)
                    state <= STOP;

                else
                    bit_index <= bit_index + 1;

            end

            STOP:
            begin
                tx <= 1;
                busy <= 0;
                state <= IDLE;
            end

        endcase

    end

end

endmodule

Level3_UART_Communication/1_UART_tb.v
`timescale 1ns/1ps

module uart_tx_tb;

reg clk;
reg reset;
reg start;
reg [7:0] data_in;

wire tx;
wire busy;

uart_tx uut (

    .clk(clk),
    .reset(reset),
    .start(start),
    .data_in(data_in),
    .tx(tx),
    .busy(busy)

);

always #5 clk = ~clk;

initial begin

    $dumpfile("1_uart_tx.vcd");
    $dumpvars(0, uart_tx_tb);

    clk = 0;
    reset = 1;
    start = 0;
    data_in = 8'b10101010;

    #10;
    reset = 0;

    #10;
    start = 1;

    #10;
    start = 0;

    #150;

    $finish;

end

endmodule

Level3_UART_Communication/1_uart_tx.vcd
$date
	Mon Jul 20 19:03:42 2026
$end
$version
	Icarus Verilog
$end
$timescale
	1ps
$end
$scope module uart_tx_tb $end
$var wire 1 ! tx $end
$var wire 1 " busy $end
$var reg 1 # clk $end
$var reg 8 $ data_in [7:0] $end
$var reg 1 % reset $end
$var reg 1 & start $end
$scope module uut $end
$var wire 1 # clk $end
$var wire 8 ' data_in [7:0] $end
$var wire 1 % reset $end
$var wire 1 & start $end
$var parameter 2 ( DATA $end
$var parameter 2 ) IDLE $end
$var parameter 2 * START $end
$var parameter 2 + STOP $end
$var reg 3 , bit_index [2:0] $end
$var reg 1 " busy $end
$var reg 8 - shift_reg [7:0] $end
$var reg 2 . state [1:0] $end
$var reg 1 ! tx $end
$upscope $end
$upscope $end
$enddefinitions $end
$comment Show the parameter values. $end
$dumpall
b11 +
b1 *
b0 )
b10 (
$end
#0
$dumpvars
b0 .
bx -
b0 ,
b10101010 '
0&
1%
b10101010 $
0#
0"
1!
$end
#5000
1#
#10000
0#
0%
#15000
1#
#20000
0#
1&
#25000
b1 .
1"
b10101010 -
1#
#30000
0#
0&
#35000
b10 .
0!
1#
#40000
0#
#45000
b1 ,
1#
#50000
0#
#55000
b10 ,
1!
1#
#60000
0#
#65000
b11 ,
0!
1#
#70000
0#
#75000
b100 ,
1!
1#
#80000
0#
#85000
b101 ,
0!
1#
#90000
0#
#95000
b110 ,
1!
1#
#100000
0#
#105000
b111 ,
0!
1#
#110000
0#
#115000
b11 .
1!
1#
#120000
0#
#125000
b0 .
0"
1#
