Level3_UART_Communication/2_UART.v
module uart_rx(

    input clk,
    input reset,
    input rx,

    output reg [7:0] data_out,
    output reg data_ready

);

reg [1:0] state;
reg [2:0] bit_index;
reg [7:0] shift_reg;

parameter IDLE  = 2'b00;
parameter START = 2'b01;
parameter DATA  = 2'b10;
parameter STOP  = 2'b11;

always @(posedge clk or posedge reset)
begin

    if(reset)
    begin
        state <= IDLE;
        bit_index <= 0;
        shift_reg <= 8'b0;
        data_out <= 8'b0;
        data_ready <= 0;
    end

    else
    begin

        data_ready <= 0;

        case(state)

            IDLE:
            begin
                if(rx == 0)
                begin
                    state <= START;
                end
            end

            START:
            begin
                bit_index <= 0;
                state <= DATA;
            end

            DATA:
            begin

                shift_reg[bit_index] <= rx;

                if(bit_index == 7)
                    state <= STOP;

                else
                    bit_index <= bit_index + 1;

            end

            STOP:
            begin

                if(rx == 1)
                begin
                    data_out <= shift_reg;
                    data_ready <= 1;
                end

                state <= IDLE;

            end

        endcase

    end

end

endmodule

Level3_UART_Communication/2_UART_tb.v
`timescale 1ns/1ps

module uart_rx_tb;

reg clk;
reg reset;
reg rx;

wire [7:0] data_out;
wire data_ready;

uart_rx uut(

    .clk(clk),
    .reset(reset),
    .rx(rx),

    .data_out(data_out),
    .data_ready(data_ready)

);

always #5 clk = ~clk;

initial
begin

    $dumpfile("2_uart_rx.vcd");
    $dumpvars(0, uart_rx_tb);

    clk = 0;
    reset = 1;
    rx = 1;

    #10;
    reset = 0;

    // Start Bit
    #10 rx = 0;

    // Data = 10101010 (LSB First)
    #10 rx = 0;
    #10 rx = 1;
    #10 rx = 0;
    #10 rx = 1;
    #10 rx = 0;
    #10 rx = 1;
    #10 rx = 0;
    #10 rx = 1;

    // Stop Bit
    #10 rx = 1;

    #40;

    $finish;

end

endmodule

Level3_UART_Communication/2_uart_rx.vcd
$date
	Sat Jul 25 11:53:29 2026
$end
$version
	Icarus Verilog
$end
$timescale
	1ps
$end
$scope module uart_rx_tb $end
$var wire 1 ! data_ready $end
$var wire 8 " data_out [7:0] $end
$var reg 1 # clk $end
$var reg 1 $ reset $end
$var reg 1 % rx $end
$scope module uut $end
$var wire 1 # clk $end
$var wire 1 $ reset $end
$var wire 1 % rx $end
$var parameter 2 & DATA $end
$var parameter 2 ' IDLE $end
$var parameter 2 ( START $end
$var parameter 2 ) STOP $end
$var reg 3 * bit_index [2:0] $end
$var reg 8 + data_out [7:0] $end
$var reg 1 ! data_ready $end
$var reg 8 , shift_reg [7:0] $end
$var reg 2 - state [1:0] $end
$upscope $end
$upscope $end
$enddefinitions $end
$comment Show the parameter values. $end
$dumpall
b11 )
b1 (
b0 '
b10 &
$end
#0
$dumpvars
b0 -
b0 ,
b0 +
b0 *
1%
1$
0#
b0 "
0!
$end
#5000
1#
#10000
0#
0$
#15000
1#
#20000
0#
0%
#25000
b1 -
1#
#30000
0#
#35000
b10 -
1#
#40000
0#
1%
#45000
b1 *
b1 ,
1#
#50000
0#
0%
#55000
b10 *
1#
#60000
0#
1%
#65000
b11 *
b101 ,
1#
#70000
0#
0%
#75000
b100 *
1#
#80000
0#
1%
#85000
b101 *
b10101 ,
1#
#90000
0#
0%
#95000
b110 *
1#
#100000
0#
1%
#105000
b111 *
b1010101 ,
1#
#110000
0#
#115000
b11 -
b11010101 ,
1#
#120000
0#
#125000
b0 -
1!
b11010101 "
b11010101 +
1#
#130000
0#
#135000
0!
1#
