Level3_UART_Communication/2_UART.v
module uart_rx(

    input clk,
    input reset,
    input rx,

    output reg [7:0] data_out,
    output reg data_ready

);

reg [1:0] state;
reg [2:0] bit_index;
reg [7:0] shift_reg;

parameter IDLE  = 2'b00;
parameter START = 2'b01;
parameter DATA  = 2'b10;
parameter STOP  = 2'b11;

always @(posedge clk or posedge reset)
begin

    if(reset)
    begin
        state <= IDLE;
        bit_index <= 0;
        shift_reg <= 8'b0;
        data_out <= 8'b0;
        data_ready <= 0;
    end

    else
    begin

        data_ready <= 0;

        case(state)

            IDLE:
            begin
                if(rx == 0)
                begin
                    state <= START;
                end
            end

            START:
            begin
                bit_index <= 0;
                state <= DATA;
            end

            DATA:
            begin

                shift_reg[bit_index] <= rx;

                if(bit_index == 7)
                    state <= STOP;

                else
                    bit_index <= bit_index + 1;

            end

            STOP:
            begin

                if(rx == 1)
                begin
                    data_out <= shift_reg;
                    data_ready <= 1;
                end

                state <= IDLE;

            end

        endcase

    end

end

endmodule

Level3_UART_Communication/1_UART.v
module uart_tx(

    input clk,
    input reset,
    input start,
    input [7:0] data_in,

    output reg tx,
    output reg busy

);

reg [1:0] state;
reg [2:0] bit_index;
reg [7:0] shift_reg;

parameter IDLE  = 2'b00;
parameter START = 2'b01;
parameter DATA  = 2'b10;
parameter STOP  = 2'b11;

always @(posedge clk or posedge reset)
begin

    if(reset)
    begin
        state <= IDLE;
        tx <= 1;
        busy <= 0;
        bit_index <= 0;
    end

    else
    begin

        case(state)

            IDLE:
            begin
                tx <= 1;
                busy <= 0;

                if(start)
                begin
                    shift_reg <= data_in;
                    bit_index <= 0;
                    busy <= 1;
                    state <= START;
                end
            end

            START:
            begin
                tx <= 0;
                state <= DATA;
            end

            DATA:
            begin

                tx <= shift_reg[bit_index];

                if(bit_index == 7)
                    state <= STOP;

                else
                    bit_index <= bit_index + 1;

            end

            STOP:
            begin
                tx <= 1;
                busy <= 0;
                state <= IDLE;
            end

        endcase

    end

end

endmodule

Level3_UART_Communication/3_UART_LOOP.v
`timescale 1ns/1ps

module uart_loop_tb;

reg clk;
reg reset;
reg start;
reg [7:0] tx_data;

// Wire connecting TX and RX
wire tx;

// Receiver outputs
wire [7:0] rx_data;
wire data_ready;

//------------------------
// UART Transmitter
//------------------------
uart_tx transmitter(

    .clk(clk),
    .reset(reset),
    .start(start),
    .data_in(tx_data),
    .tx(tx)

);

//------------------------
// UART Receiver
//------------------------
uart_rx receiver(

    .clk(clk),
    .reset(reset),
    .rx(tx),

    .data_out(rx_data),
    .data_ready(data_ready)

);

// Clock
always #5 clk = ~clk;

initial
begin

    $dumpfile("3_uart_loop.vcd");
    $dumpvars(0, uart_loop_tb);

    clk = 0;
    reset = 1;
    start = 0;
    tx_data = 8'hAA;

    #10;
    reset = 0;

    // Begin transmission
    #10;
    start = 1;

    #10;
    start = 0;

    // Wait until transmission completes
    #250;

    $finish;

end

endmodule

Level3_UART_Communication/3_uart_loop.vcd
$date
	Sat Jul 25 12:08:08 2026
$end
$version
	Icarus Verilog
$end
$timescale
	1ps
$end
$scope module uart_loop_tb $end
$var wire 1 ! tx $end
$var wire 8 " rx_data [7:0] $end
$var wire 1 # data_ready $end
$var reg 1 $ clk $end
$var reg 1 % reset $end
$var reg 1 & start $end
$var reg 8 ' tx_data [7:0] $end
$scope module receiver $end
$var wire 1 $ clk $end
$var wire 1 % reset $end
$var wire 1 ! rx $end
$var parameter 2 ( DATA $end
$var parameter 2 ) IDLE $end
$var parameter 2 * START $end
$var parameter 2 + STOP $end
$var reg 3 , bit_index [2:0] $end
$var reg 8 - data_out [7:0] $end
$var reg 1 # data_ready $end
$var reg 8 . shift_reg [7:0] $end
$var reg 2 / state [1:0] $end
$upscope $end
$scope module transmitter $end
$var wire 1 $ clk $end
$var wire 8 0 data_in [7:0] $end
$var wire 1 % reset $end
$var wire 1 & start $end
$var parameter 2 1 DATA $end
$var parameter 2 2 IDLE $end
$var parameter 2 3 START $end
$var parameter 2 4 STOP $end
$var reg 3 5 bit_index [2:0] $end
$var reg 1 6 busy $end
$var reg 8 7 shift_reg [7:0] $end
$var reg 2 8 state [1:0] $end
$var reg 1 ! tx $end
$upscope $end
$upscope $end
$enddefinitions $end
$comment Show the parameter values. $end
$dumpall
b11 4
b1 3
b0 2
b10 1
b11 +
b1 *
b0 )
b10 (
$end
#0
$dumpvars
b0 8
bx 7
06
b0 5
b10101010 0
b0 /
b0 .
b0 -
b0 ,
b10101010 '
0&
1%
0$
0#
b0 "
1!
$end
#5000
1$
#10000
0$
0%
#15000
1$
#20000
0$
1&
#25000
b1 8
16
b10101010 7
1$
#30000
0$
0&
#35000
b10 8
0!
1$
#40000
0$
#45000
b1 /
b1 5
1$
#50000
0$
#55000
b10 5
1!
b10 /
1$
#60000
0$
#65000
b1 ,
b1 .
b11 5
0!
1$
#70000
0$
#75000
b100 5
1!
b10 ,
1$
#80000
0$
#85000
b11 ,
b101 .
b101 5
0!
1$
#90000
0$
#95000
b110 5
1!
b100 ,
1$
#100000
0$
#105000
b101 ,
b10101 .
b111 5
0!
1$
#110000
0$
#115000
b11 8
1!
b110 ,
1$
#120000
0$
#125000
b111 ,
b1010101 .
b0 8
06
1$
#130000
0$
#135000
b11 /
b11010101 .
1$
#140000
0$
#145000
b0 /
1#
b11010101 "
b11010101 -
1$
#150000
0$
#155000
0#
1$
