Level1_Digital_Logic/2_full_adder.v
module full_adder(
    input A,
    input B,
    input Cin,
    output SUM,
    output Cout
);

assign SUM  = A ^ B ^ Cin;
assign Cout = (A & B) | (B & Cin) | (A & Cin);

endmodule

Level1_Digital_Logic/2_full_adder_tb.v
`timescale 1ns/1ps

module full_adder_tb;

reg A, B, Cin;
wire SUM, Cout;

full_adder uut (
    .A(A),
    .B(B),
    .Cin(Cin),
    .SUM(SUM),
    .Cout(Cout)
);

initial begin

    $dumpfile("full_adder.vcd");
    $dumpvars(0, full_adder_tb);

    A=0; B=0; Cin=0; #10;
    A=0; B=0; Cin=1; #10;
    A=0; B=1; Cin=0; #10;
    A=0; B=1; Cin=1; #10;
    A=1; B=0; Cin=0; #10;
    A=1; B=0; Cin=1; #10;
    A=1; B=1; Cin=0; #10;
    A=1; B=1; Cin=1; #10;

    $finish;

end

endmodule

Level1_Digital_Logic/2_full_adder.vcd
$date
	Tue Jul 14 19:08:49 2026
$end
$version
	Icarus Verilog
$end
$timescale
	1ps
$end
$scope module full_adder_tb $end
$var wire 1 ! SUM $end
$var wire 1 " Cout $end
$var reg 1 # A $end
$var reg 1 $ B $end
$var reg 1 % Cin $end
$scope module uut $end
$var wire 1 # A $end
$var wire 1 $ B $end
$var wire 1 % Cin $end
$var wire 1 " Cout $end
$var wire 1 ! SUM $end
$upscope $end
$upscope $end
$enddefinitions $end
$comment Show the parameter values. $end
$dumpall
$end
#0
$dumpvars
0%
0$
0#
0"
0!
$end
#10000
1!
1%
#20000
0%
1$
#30000
1"
0!
1%
#40000
0"
1!
0%
0$
1#
#50000
1"
0!
1%
#60000
0%
1$
#70000
1!
1%
