Level1_Digital_Logic/1_half_adder.v
module half_adder(
    input A,
    input B,
    output SUM,
    output CARRY
);

assign SUM = A ^ B;
assign CARRY = A & B;

endmodule

Level1_Digital_Logic/3_multiplier.v
module multiplier_2x2(
    input  [1:0] A,
    input  [1:0] B,
    output [3:0] P
);

wire pp0, pp1, pp2, pp3;
wire carry1;

// Partial Products

assign pp0 = A[0] & B[0];
assign pp1 = A[1] & B[0];
assign pp2 = A[0] & B[1];
assign pp3 = A[1] & B[1];

// Bit 0

assign P[0] = pp0;

// Add middle terms

half_adder HA1(
    .A(pp1),
    .B(pp2),
    .SUM(P[1]),
    .CARRY(carry1)
);

// Add final carry

half_adder HA2(
    .A(pp3),
    .B(carry1),
    .SUM(P[2]),
    .CARRY(P[3])
);

endmodule

Level1_Digital_Logic/3_multiplier_tb.v
`timescale 1ns/1ps

module multiplier_2x2_tb;

reg [1:0] A;
reg [1:0] B;

wire [3:0] P;

multiplier_2x2 uut(
    .A(A),
    .B(B),
    .P(P)
);

integer i, j;

initial begin

    $dumpfile("3_multiplier_2x2.vcd");
    $dumpvars(0, multiplier_2x2_tb);

    for(i = 0; i < 4; i = i + 1)
    begin
        for(j = 0; j < 4; j = j + 1)
        begin
            A = i;
            B = j;
            #10;
        end
    end

    $finish;
end

endmodule

Level1_Digital_Logic/3_multiplier_2x2.vcd
$date
	Tue Jul 14 19:25:27 2026
$end
$version
	Icarus Verilog
$end
$timescale
	1ps
$end
$scope module multiplier_2x2_tb $end
$var wire 4 ! P [3:0] $end
$var reg 2 " A [1:0] $end
$var reg 2 # B [1:0] $end
$var integer 32 $ i [31:0] $end
$var integer 32 % j [31:0] $end
$scope module uut $end
$var wire 2 & A [1:0] $end
$var wire 2 ' B [1:0] $end
$var wire 1 ( pp0 $end
$var wire 1 ) pp1 $end
$var wire 1 * pp2 $end
$var wire 1 + pp3 $end
$var wire 1 , carry1 $end
$var wire 4 - P [3:0] $end
$scope module HA1 $end
$var wire 1 ) A $end
$var wire 1 * B $end
$var wire 1 , CARRY $end
$var wire 1 . SUM $end
$upscope $end
$scope module HA2 $end
$var wire 1 + A $end
$var wire 1 , B $end
$var wire 1 / CARRY $end
$var wire 1 0 SUM $end
$upscope $end
$upscope $end
$upscope $end
$enddefinitions $end
$comment Show the parameter values. $end
$dumpall
$end
#0
$dumpvars
00
0/
0.
b0 -
0,
0+
0*
0)
0(
b0 '
b0 &
b0 %
b0 $
b0 #
b0 "
b0 !
$end
#10000
b1 #
b1 '
b1 %
#20000
b10 #
b10 '
b10 %
#30000
b11 #
b11 '
b11 %
#40000
b0 #
b0 '
b1 "
b1 &
b1 $
b0 %
#50000
b1 !
b1 -
1(
b1 #
b1 '
b1 %
#60000
1.
b10 !
b10 -
0(
1*
b10 #
b10 '
b10 %
#70000
b11 !
b11 -
1(
b11 #
b11 '
b11 %
#80000
0.
b0 !
b0 -
0(
0*
b0 #
b0 '
b10 "
b10 &
b10 $
b0 %
#90000
b10 !
b10 -
1.
1)
b1 #
b1 '
b1 %
#100000
0.
b100 !
b100 -
10
0)
1+
b10 #
b10 '
b10 %
#110000
b110 !
b110 -
1.
1)
b11 #
b11 '
b11 %
#120000
0.
b0 !
b0 -
00
0)
0+
b0 #
b0 '
b11 "
b11 &
b11 $
b0 %
#130000
1.
b11 !
b11 -
1(
1)
b1 #
b1 '
b1 %
#140000
10
b110 !
b110 -
0(
0)
1*
1+
b10 #
b10 '
b10 %
#150000
00
1/
0.
1,
b1001 !
b1001 -
1(
1)
b11 #
b11 '
b11 %
#160000
b100 $
b100 %
