Level1_Digital_Logic/4_multiplexer.v
module mux_8to1(
    input  [7:0] I,
    input  [2:0] S,
    output reg Y
);

always @(*) begin

    case(S)

        3'b000: Y = I[0];
        3'b001: Y = I[1];
        3'b010: Y = I[2];
        3'b011: Y = I[3];
        3'b100: Y = I[4];
        3'b101: Y = I[5];
        3'b110: Y = I[6];
        3'b111: Y = I[7];

    endcase

end

endmodule

Level1_Digital_Logic/4_multiplexer_tb.v
`timescale 1ns/1ps

module mux_8to1_tb;

reg [7:0] I;
reg [2:0] S;

wire Y;

mux_8to1 uut(
    .I(I),
    .S(S),
    .Y(Y)
);

initial begin

    $dumpfile("4_mux_8to1.vcd");
    $dumpvars(0, mux_8to1_tb);

    I = 8'b10110010;

    S = 3'b000; #10;
    S = 3'b001; #10;
    S = 3'b010; #10;
    S = 3'b011; #10;
    S = 3'b100; #10;
    S = 3'b101; #10;
    S = 3'b110; #10;
    S = 3'b111; #10;

    $finish;

end

endmodule

Level1_Digital_Logic/4_mux_8to1.vcd
$date
	Wed Jul 15 19:21:09 2026
$end
$version
	Icarus Verilog
$end
$timescale
	1ps
$end
$scope module mux_8to1_tb $end
$var wire 1 ! Y $end
$var reg 8 " I [7:0] $end
$var reg 3 # S [2:0] $end
$scope module uut $end
$var wire 8 $ I [7:0] $end
$var wire 3 % S [2:0] $end
$var reg 1 ! Y $end
$upscope $end
$upscope $end
$enddefinitions $end
$comment Show the parameter values. $end
$dumpall
$end
#0
$dumpvars
b0 %
b10110010 $
b0 #
b10110010 "
0!
$end
#10000
1!
b1 #
b1 %
#20000
0!
b10 #
b10 %
#30000
b11 #
b11 %
#40000
1!
b100 #
b100 %
#50000
b101 #
b101 %
#60000
0!
b110 #
b110 %
#70000
1!
b111 #
b111 %
